maasta/__init__.py
maasta/__main__.py
maasta/maasta.py
maasta/utils.py
maasta-1.0.0.dist-info/LICENSE
maasta-1.0.0.dist-info/METADATA
maasta-1.0.0.dist-info/WHEEL
maasta-1.0.0.dist-info/top_level.txt
maasta-1.0.0.dist-info/zip-safe
maasta-1.0.0.dist-info/RECORD
