Metadata-Version: 2.1
Name: maasta
Version: 1.0.0
Summary: MAAS Terraform Ansible
Home-page: https://github.com/ssbostan/maasta
Author: Saeid Bostandoust
Author-email: ssbostan@yahoo.com
License: Apache License 2.0
Classifier: Development Status :: 5 - Production/Stable
Classifier: Environment :: Console
Classifier: Framework :: Ansible
Classifier: Intended Audience :: Information Technology
Classifier: Intended Audience :: System Administrators
Classifier: License :: OSI Approved :: Apache Software License
Classifier: Operating System :: OS Independent
Classifier: Programming Language :: Python :: 3 :: Only
Classifier: Topic :: System :: Installation/Setup
License-File: LICENSE
Requires-Dist: aiohttp (==3.8.3)
Requires-Dist: aiosignal (==1.2.0)
Requires-Dist: argcomplete (==2.0.0)
Requires-Dist: async-timeout (==4.0.2)
Requires-Dist: attrs (==22.1.0)
Requires-Dist: certifi (==2022.9.24)
Requires-Dist: cffi (==1.15.1)
Requires-Dist: charset-normalizer (==2.1.1)
Requires-Dist: colorclass (==2.2.2)
Requires-Dist: decorator (==5.1.1)
Requires-Dist: frozenlist (==1.3.1)
Requires-Dist: idna (==3.4)
Requires-Dist: macaroonbakery (==1.3.1)
Requires-Dist: multidict (==6.0.2)
Requires-Dist: oauthlib (==3.2.1)
Requires-Dist: protobuf (==3.20.3)
Requires-Dist: pycparser (==2.21)
Requires-Dist: pymacaroons (==0.13.0)
Requires-Dist: pymongo (==4.2.0)
Requires-Dist: PyNaCl (==1.5.0)
Requires-Dist: pyRFC3339 (==1.1)
Requires-Dist: python-libmaas (==0.6.8)
Requires-Dist: pytz (==2022.2.1)
Requires-Dist: PyYAML (==6.0)
Requires-Dist: requests (==2.28.1)
Requires-Dist: six (==1.16.0)
Requires-Dist: terminaltables (==3.1.10)
Requires-Dist: urllib3 (==1.26.12)
Requires-Dist: validators (==0.20.0)
Requires-Dist: yarl (==1.8.1)
